netils/__init__.py
netils/netils.py
netils-0.0.1.dist-info/LICENSE.txt
netils-0.0.1.dist-info/METADATA
netils-0.0.1.dist-info/RECORD
netils-0.0.1.dist-info/WHEEL
netils-0.0.1.dist-info/top_level.txt
